{
  "credit": "Made with Blockbench",
  "elements": [
    {
      "name": "kusanag512_blade_1",
      "from": [
        4.5625,
        8,
        7.8125
      ],
      "to": [
        15.53125,
        8.05,
        7.84375
      ],
      "faces": {
        "north": {
          "uv": [
            15.53125,
            7.8125,
            4.5625,
            7.84375
          ],
          "texture": "#2"
        },
        "east": {
          "uv": [
            15.5,
            7.8125,
            15.53125,
            7.84375
          ],
          "rotation": 90,
          "texture": "#2"
        },
        "south": {
          "uv": [
            4.5625,
            7.8125,
            15.53125,
            7.84375
          ],
          "texture": "#2"
        },
        "west": {
          "uv": [
            4.5625,
            7.8125,
            4.59375,
            7.84375
          ],
          "rotation": 270,
          "texture": "#2"
        },
        "up": {
          "uv": [
            4.5625,
            7.8125,
            15.53125,
            7.84375
          ],
          "texture": "#2"
        },
        "down": {
          "uv": [
            4.5625,
            7.84375,
            15.53125,
            7.8125
          ],
          "texture": "#2"
        }
      }
    },
    {
      "name": "kusanag512_blade_2",
      "from": [
        4.5625,
        8,
        7.84375
      ],
      "to": [
        15.53125,
        8.05,
        7.875
      ],
      "faces": {
        "north": {
          "uv": [
            15.53125,
            7.84375,
            4.5625,
            7.875
          ],
          "texture": "#2"
        },
        "east": {
          "uv": [
            15.5,
            7.84375,
            15.53125,
            7.875
          ],
          "rotation": 90,
          "texture": "#2"
        },
        "south": {
          "uv": [
            4.5625,
            7.84375,
            15.53125,
            7.875
          ],
          "texture": "#2"
        },
        "west": {
          "uv": [
            4.5625,
            7.84375,
            4.59375,
            7.875
          ],
          "rotation": 270,
          "texture": "#2"
        },
        "up": {
          "uv": [
            4.5625,
            7.84375,
            15.53125,
            7.875
          ],
          "texture": "#2"
        },
        "down": {
          "uv": [
            4.5625,
            7.875,
            15.53125,
            7.84375
          ],
          "texture": "#2"
        }
      }
    },
    {
      "name": "kusanag512_blade_3",
      "from": [
        4.5625,
        8,
        7.875
      ],
      "to": [
        15.5625,
        8.05,
        7.90625
      ],
      "faces": {
        "north": {
          "uv": [
            15.5625,
            7.875,
            4.5625,
            7.90625
          ],
          "texture": "#2"
        },
        "east": {
          "uv": [
            15.53125,
            7.875,
            15.5625,
            7.90625
          ],
          "rotation": 90,
          "texture": "#2"
        },
        "south": {
          "uv": [
            4.5625,
            7.875,
            15.5625,
            7.90625
          ],
          "texture": "#2"
        },
        "west": {
          "uv": [
            4.5625,
            7.875,
            4.59375,
            7.90625
          ],
          "rotation": 270,
          "texture": "#2"
        },
        "up": {
          "uv": [
            4.5625,
            7.875,
            15.5625,
            7.90625
          ],
          "texture": "#2"
        },
        "down": {
          "uv": [
            4.5625,
            7.90625,
            15.5625,
            7.875
          ],
          "texture": "#2"
        }
      }
    },
    {
      "name": "kusanag512_blade_4",
      "from": [
        4.5625,
        8,
        7.90625
      ],
      "to": [
        15.53125,
        8.05,
        7.9375
      ],
      "faces": {
        "north": {
          "uv": [
            15.53125,
            7.90625,
            4.5625,
            7.9375
          ],
          "texture": "#2"
        },
        "east": {
          "uv": [
            15.5,
            7.90625,
            15.53125,
            7.9375
          ],
          "rotation": 90,
          "texture": "#2"
        },
        "south": {
          "uv": [
            4.5625,
            7.90625,
            15.53125,
            7.9375
          ],
          "texture": "#2"
        },
        "west": {
          "uv": [
            4.5625,
            7.90625,
            4.59375,
            7.9375
          ],
          "rotation": 270,
          "texture": "#2"
        },
        "up": {
          "uv": [
            4.5625,
            7.90625,
            15.53125,
            7.9375
          ],
          "texture": "#2"
        },
        "down": {
          "uv": [
            4.5625,
            7.9375,
            15.53125,
            7.90625
          ],
          "texture": "#2"
        }
      }
    },
    {
      "name": "kusanag512_blade_5",
      "from": [
        4.5625,
        8,
        7.9375
      ],
      "to": [
        15.5,
        8.05,
        7.96875
      ],
      "faces": {
        "north": {
          "uv": [
            15.5,
            7.9375,
            4.5625,
            7.96875
          ],
          "texture": "#2"
        },
        "east": {
          "uv": [
            15.46875,
            7.9375,
            15.5,
            7.96875
          ],
          "rotation": 90,
          "texture": "#2"
        },
        "south": {
          "uv": [
            4.5625,
            7.9375,
            15.5,
            7.96875
          ],
          "texture": "#2"
        },
        "west": {
          "uv": [
            4.5625,
            7.9375,
            4.59375,
            7.96875
          ],
          "rotation": 270,
          "texture": "#2"
        },
        "up": {
          "uv": [
            4.5625,
            7.9375,
            15.5,
            7.96875
          ],
          "texture": "#2"
        },
        "down": {
          "uv": [
            4.5625,
            7.96875,
            15.5,
            7.9375
          ],
          "texture": "#2"
        }
      }
    },
    {
      "name": "kusanag512_blade_6",
      "from": [
        4.5625,
        8,
        7.96875
      ],
      "to": [
        15.5,
        8.05,
        8
      ],
      "faces": {
        "north": {
          "uv": [
            15.5,
            7.96875,
            4.5625,
            8
          ],
          "texture": "#2"
        },
        "east": {
          "uv": [
            15.46875,
            7.96875,
            15.5,
            8
          ],
          "rotation": 90,
          "texture": "#2"
        },
        "south": {
          "uv": [
            4.5625,
            7.96875,
            15.5,
            8
          ],
          "texture": "#2"
        },
        "west": {
          "uv": [
            4.5625,
            7.96875,
            4.59375,
            8
          ],
          "rotation": 270,
          "texture": "#2"
        },
        "up": {
          "uv": [
            4.5625,
            7.96875,
            15.5,
            8
          ],
          "texture": "#2"
        },
        "down": {
          "uv": [
            4.5625,
            8,
            15.5,
            7.96875
          ],
          "texture": "#2"
        }
      }
    },
    {
      "name": "kusanag512_blade_7",
      "from": [
        4.5625,
        8,
        8
      ],
      "to": [
        15.5,
        8.05,
        8.03125
      ],
      "faces": {
        "north": {
          "uv": [
            15.5,
            8,
            4.5625,
            8.03125
          ],
          "texture": "#2"
        },
        "east": {
          "uv": [
            15.46875,
            8,
            15.5,
            8.03125
          ],
          "rotation": 90,
          "texture": "#2"
        },
        "south": {
          "uv": [
            4.5625,
            8,
            15.5,
            8.03125
          ],
          "texture": "#2"
        },
        "west": {
          "uv": [
            4.5625,
            8,
            4.59375,
            8.03125
          ],
          "rotation": 270,
          "texture": "#2"
        },
        "up": {
          "uv": [
            4.5625,
            8,
            15.5,
            8.03125
          ],
          "texture": "#2"
        },
        "down": {
          "uv": [
            4.5625,
            8.03125,
            15.5,
            8
          ],
          "texture": "#2"
        }
      }
    },
    {
      "name": "kusanag512_blade_8",
      "from": [
        4.5625,
        8,
        8.03125
      ],
      "to": [
        15.4375,
        8.05,
        8.0625
      ],
      "faces": {
        "north": {
          "uv": [
            15.4375,
            8.03125,
            4.5625,
            8.0625
          ],
          "texture": "#2"
        },
        "east": {
          "uv": [
            15.40625,
            8.03125,
            15.4375,
            8.0625
          ],
          "rotation": 90,
          "texture": "#2"
        },
        "south": {
          "uv": [
            4.5625,
            8.03125,
            15.4375,
            8.0625
          ],
          "texture": "#2"
        },
        "west": {
          "uv": [
            4.5625,
            8.03125,
            4.59375,
            8.0625
          ],
          "rotation": 270,
          "texture": "#2"
        },
        "up": {
          "uv": [
            4.5625,
            8.03125,
            15.4375,
            8.0625
          ],
          "texture": "#2"
        },
        "down": {
          "uv": [
            4.5625,
            8.0625,
            15.4375,
            8.03125
          ],
          "texture": "#2"
        }
      }
    },
    {
      "name": "kusanag512_blade_9",
      "from": [
        4.5625,
        8,
        8.0625
      ],
      "to": [
        15.4375,
        8.045,
        8.09375
      ],
      "faces": {
        "north": {
          "uv": [
            15.4375,
            8.0625,
            4.5625,
            8.09375
          ],
          "texture": "#2"
        },
        "east": {
          "uv": [
            15.40625,
            8.0625,
            15.4375,
            8.09375
          ],
          "rotation": 90,
          "texture": "#2"
        },
        "south": {
          "uv": [
            4.5625,
            8.0625,
            15.4375,
            8.09375
          ],
          "texture": "#2"
        },
        "west": {
          "uv": [
            4.5625,
            8.0625,
            4.59375,
            8.09375
          ],
          "rotation": 270,
          "texture": "#2"
        },
        "up": {
          "uv": [
            4.5625,
            8.0625,
            15.4375,
            8.09375
          ],
          "texture": "#2"
        },
        "down": {
          "uv": [
            4.5625,
            8.09375,
            15.4375,
            8.0625
          ],
          "texture": "#2"
        }
      }
    },
    {
      "name": "kusanag512_blade_10",
      "from": [
        4.5625,
        8,
        8.09375
      ],
      "to": [
        15.40625,
        8.04,
        8.125
      ],
      "faces": {
        "north": {
          "uv": [
            15.40625,
            8.09375,
            4.5625,
            8.125
          ],
          "texture": "#2"
        },
        "east": {
          "uv": [
            15.375,
            8.09375,
            15.40625,
            8.125
          ],
          "rotation": 90,
          "texture": "#2"
        },
        "south": {
          "uv": [
            4.5625,
            8.09375,
            15.40625,
            8.125
          ],
          "texture": "#2"
        },
        "west": {
          "uv": [
            4.5625,
            8.09375,
            4.59375,
            8.125
          ],
          "rotation": 270,
          "texture": "#2"
        },
        "up": {
          "uv": [
            4.5625,
            8.09375,
            15.40625,
            8.125
          ],
          "texture": "#2"
        },
        "down": {
          "uv": [
            4.5625,
            8.125,
            15.40625,
            8.09375
          ],
          "texture": "#2"
        }
      }
    },
    {
      "name": "kusanag512_blade_11",
      "from": [
        4.5625,
        8,
        8.125
      ],
      "to": [
        15.40625,
        8.035,
        8.15625
      ],
      "faces": {
        "north": {
          "uv": [
            15.40625,
            8.125,
            4.5625,
            8.15625
          ],
          "texture": "#2"
        },
        "east": {
          "uv": [
            15.375,
            8.125,
            15.40625,
            8.15625
          ],
          "rotation": 90,
          "texture": "#2"
        },
        "south": {
          "uv": [
            4.5625,
            8.125,
            15.40625,
            8.15625
          ],
          "texture": "#2"
        },
        "west": {
          "uv": [
            4.5625,
            8.125,
            4.59375,
            8.15625
          ],
          "rotation": 270,
          "texture": "#2"
        },
        "up": {
          "uv": [
            4.5625,
            8.125,
            15.40625,
            8.15625
          ],
          "texture": "#2"
        },
        "down": {
          "uv": [
            4.5625,
            8.15625,
            15.40625,
            8.125
          ],
          "texture": "#2"
        }
      }
    },
    {
      "name": "kusanag512_blade_12",
      "from": [
        4.5625,
        8,
        8.15625
      ],
      "to": [
        15.375,
        8.03,
        8.1875
      ],
      "faces": {
        "north": {
          "uv": [
            15.375,
            8.15625,
            4.5625,
            8.1875
          ],
          "texture": "#2"
        },
        "east": {
          "uv": [
            15.34375,
            8.15625,
            15.375,
            8.1875
          ],
          "rotation": 90,
          "texture": "#2"
        },
        "south": {
          "uv": [
            4.5625,
            8.15625,
            15.375,
            8.1875
          ],
          "texture": "#2"
        },
        "west": {
          "uv": [
            4.5625,
            8.15625,
            4.59375,
            8.1875
          ],
          "rotation": 270,
          "texture": "#2"
        },
        "up": {
          "uv": [
            4.5625,
            8.15625,
            15.375,
            8.1875
          ],
          "texture": "#2"
        },
        "down": {
          "uv": [
            4.5625,
            8.1875,
            15.375,
            8.15625
          ],
          "texture": "#2"
        }
      }
    },
    {
      "name": "kusanag512_blade_13",
      "from": [
        4.5625,
        8,
        8.1875
      ],
      "to": [
        15.3125,
        8.025,
        8.21875
      ],
      "faces": {
        "north": {
          "uv": [
            15.3125,
            8.1875,
            4.5625,
            8.21875
          ],
          "texture": "#2"
        },
        "east": {
          "uv": [
            15.28125,
            8.1875,
            15.3125,
            8.21875
          ],
          "rotation": 90,
          "texture": "#2"
        },
        "south": {
          "uv": [
            4.5625,
            8.1875,
            15.3125,
            8.21875
          ],
          "texture": "#2"
        },
        "west": {
          "uv": [
            4.5625,
            8.1875,
            4.59375,
            8.21875
          ],
          "rotation": 270,
          "texture": "#2"
        },
        "up": {
          "uv": [
            4.5625,
            8.1875,
            15.3125,
            8.21875
          ],
          "texture": "#2"
        },
        "down": {
          "uv": [
            4.5625,
            8.21875,
            15.3125,
            8.1875
          ],
          "texture": "#2"
        }
      }
    },
    {
      "name": "kusanag512_blade_14",
      "from": [
        4.5625,
        8,
        8.21875
      ],
      "to": [
        15.3125,
        8.02,
        8.25
      ],
      "faces": {
        "north": {
          "uv": [
            15.3125,
            8.21875,
            4.5625,
            8.25
          ],
          "texture": "#2"
        },
        "east": {
          "uv": [
            15.28125,
            8.21875,
            15.3125,
            8.25
          ],
          "rotation": 90,
          "texture": "#2"
        },
        "south": {
          "uv": [
            4.5625,
            8.21875,
            15.3125,
            8.25
          ],
          "texture": "#2"
        },
        "west": {
          "uv": [
            4.5625,
            8.21875,
            4.59375,
            8.25
          ],
          "rotation": 270,
          "texture": "#2"
        },
        "up": {
          "uv": [
            4.5625,
            8.21875,
            15.3125,
            8.25
          ],
          "texture": "#2"
        },
        "down": {
          "uv": [
            4.5625,
            8.25,
            15.3125,
            8.21875
          ],
          "texture": "#2"
        }
      }
    },
    {
      "name": "kusanag512_blade_15",
      "from": [
        4.5625,
        8,
        8.25
      ],
      "to": [
        15.28125,
        8.015,
        8.28125
      ],
      "faces": {
        "north": {
          "uv": [
            15.28125,
            8.25,
            4.5625,
            8.28125
          ],
          "texture": "#2"
        },
        "east": {
          "uv": [
            15.25,
            8.25,
            15.28125,
            8.28125
          ],
          "rotation": 90,
          "texture": "#2"
        },
        "south": {
          "uv": [
            4.5625,
            8.25,
            15.28125,
            8.28125
          ],
          "texture": "#2"
        },
        "west": {
          "uv": [
            4.5625,
            8.25,
            4.59375,
            8.28125
          ],
          "rotation": 270,
          "texture": "#2"
        },
        "up": {
          "uv": [
            4.5625,
            8.25,
            15.28125,
            8.28125
          ],
          "texture": "#2"
        },
        "down": {
          "uv": [
            4.5625,
            8.28125,
            15.28125,
            8.25
          ],
          "texture": "#2"
        }
      }
    },
    {
      "name": "kusanag512_blade_16",
      "from": [
        4.5625,
        8,
        8.28125
      ],
      "to": [
        15.25,
        8.01,
        8.3125
      ],
      "faces": {
        "north": {
          "uv": [
            15.25,
            8.28125,
            4.5625,
            8.3125
          ],
          "texture": "#2"
        },
        "east": {
          "uv": [
            15.21875,
            8.28125,
            15.25,
            8.3125
          ],
          "rotation": 90,
          "texture": "#2"
        },
        "south": {
          "uv": [
            4.5625,
            8.28125,
            15.25,
            8.3125
          ],
          "texture": "#2"
        },
        "west": {
          "uv": [
            4.5625,
            8.28125,
            4.59375,
            8.3125
          ],
          "rotation": 270,
          "texture": "#2"
        },
        "up": {
          "uv": [
            4.5625,
            8.28125,
            15.25,
            8.3125
          ],
          "texture": "#2"
        },
        "down": {
          "uv": [
            4.5625,
            8.3125,
            15.25,
            8.28125
          ],
          "texture": "#2"
        }
      }
    },
    {
      "name": "kusanag512_blade_17",
      "from": [
        4.5625,
        8,
        8.3125
      ],
      "to": [
        15.21875,
        8.005,
        8.34375
      ],
      "faces": {
        "north": {
          "uv": [
            15.21875,
            8.3125,
            4.5625,
            8.34375
          ],
          "texture": "#2"
        },
        "east": {
          "uv": [
            15.1875,
            8.3125,
            15.21875,
            8.34375
          ],
          "rotation": 90,
          "texture": "#2"
        },
        "south": {
          "uv": [
            4.5625,
            8.3125,
            15.21875,
            8.34375
          ],
          "texture": "#2"
        },
        "west": {
          "uv": [
            4.5625,
            8.3125,
            4.59375,
            8.34375
          ],
          "rotation": 270,
          "texture": "#2"
        },
        "up": {
          "uv": [
            4.5625,
            8.3125,
            15.21875,
            8.34375
          ],
          "texture": "#2"
        },
        "down": {
          "uv": [
            4.5625,
            8.34375,
            15.21875,
            8.3125
          ],
          "texture": "#2"
        }
      }
    },
    {
      "name": "kusanag512_blade_29",
      "from": [
        7.5,
        8,
        8.34375
      ],
      "to": [
        15.125,
        8,
        8.375
      ],
      "faces": {
        "north": {
          "uv": [
            15.125,
            8.34375,
            7.5,
            8.375
          ],
          "texture": "#2"
        },
        "east": {
          "uv": [
            15.09375,
            8.34375,
            15.125,
            8.375
          ],
          "rotation": 90,
          "texture": "#2"
        },
        "south": {
          "uv": [
            7.5,
            8.34375,
            15.125,
            8.375
          ],
          "texture": "#2"
        },
        "west": {
          "uv": [
            7.5,
            8.34375,
            7.53125,
            8.375
          ],
          "rotation": 270,
          "texture": "#2"
        },
        "up": {
          "uv": [
            7.5,
            8.34375,
            15.125,
            8.375
          ],
          "texture": "#2"
        },
        "down": {
          "uv": [
            7.5,
            8.375,
            15.125,
            8.34375
          ],
          "texture": "#2"
        }
      }
    },
    {
      "name": "kusanag522_blade_2",
      "from": [
        4.5625,
        7.95,
        7.8125
      ],
      "to": [
        15.53125,
        8,
        7.84375
      ],
      "rotation": {
        "angle": 0,
        "axis": "y",
        "origin": [
          0,
          16,
          0
        ]
      },
      "faces": {
        "north": {
          "uv": [
            15.53125,
            7.84375,
            4.5625,
            7.8125
          ],
          "texture": "#2"
        },
        "east": {
          "uv": [
            15.53125,
            7.8125,
            15.5,
            7.84375
          ],
          "rotation": 90,
          "texture": "#2"
        },
        "south": {
          "uv": [
            4.5625,
            7.84375,
            15.53125,
            7.8125
          ],
          "texture": "#2"
        },
        "west": {
          "uv": [
            4.59375,
            7.8125,
            4.5625,
            7.84375
          ],
          "rotation": 270,
          "texture": "#2"
        },
        "up": {
          "uv": [
            4.5625,
            7.8125,
            15.53125,
            7.84375
          ],
          "texture": "#2"
        },
        "down": {
          "uv": [
            4.5625,
            7.84375,
            15.53125,
            7.8125
          ],
          "texture": "#2"
        }
      }
    },
    {
      "name": "kusanag513_blade_3",
      "from": [
        4.5625,
        7.95,
        7.84375
      ],
      "to": [
        15.53125,
        8,
        7.875
      ],
      "rotation": {
        "angle": 0,
        "axis": "y",
        "origin": [
          0,
          16,
          0
        ]
      },
      "faces": {
        "north": {
          "uv": [
            15.53125,
            7.875,
            4.5625,
            7.84375
          ],
          "texture": "#2"
        },
        "east": {
          "uv": [
            15.53125,
            7.84375,
            15.5,
            7.875
          ],
          "rotation": 90,
          "texture": "#2"
        },
        "south": {
          "uv": [
            4.5625,
            7.875,
            15.53125,
            7.84375
          ],
          "texture": "#2"
        },
        "west": {
          "uv": [
            4.59375,
            7.84375,
            4.5625,
            7.875
          ],
          "rotation": 270,
          "texture": "#2"
        },
        "up": {
          "uv": [
            4.5625,
            7.84375,
            15.53125,
            7.875
          ],
          "texture": "#2"
        },
        "down": {
          "uv": [
            4.5625,
            7.875,
            15.53125,
            7.84375
          ],
          "texture": "#2"
        }
      }
    },
    {
      "name": "kusanag512_blade_4",
      "from": [
        4.5625,
        7.95,
        7.875
      ],
      "to": [
        15.5625,
        8,
        7.90625
      ],
      "rotation": {
        "angle": 0,
        "axis": "y",
        "origin": [
          0,
          16,
          0
        ]
      },
      "faces": {
        "north": {
          "uv": [
            15.5625,
            7.90625,
            4.5625,
            7.875
          ],
          "texture": "#2"
        },
        "east": {
          "uv": [
            15.5625,
            7.875,
            15.53125,
            7.90625
          ],
          "rotation": 90,
          "texture": "#2"
        },
        "south": {
          "uv": [
            4.5625,
            7.90625,
            15.5625,
            7.875
          ],
          "texture": "#2"
        },
        "west": {
          "uv": [
            4.59375,
            7.875,
            4.5625,
            7.90625
          ],
          "rotation": 270,
          "texture": "#2"
        },
        "up": {
          "uv": [
            4.5625,
            7.875,
            15.5625,
            7.90625
          ],
          "texture": "#2"
        },
        "down": {
          "uv": [
            4.5625,
            7.90625,
            15.5625,
            7.875
          ],
          "texture": "#2"
        }
      }
    },
    {
      "name": "kusanag512_blade_5",
      "from": [
        4.5625,
        7.95,
        7.90625
      ],
      "to": [
        15.53125,
        8,
        7.9375
      ],
      "rotation": {
        "angle": 0,
        "axis": "y",
        "origin": [
          0,
          16,
          0
        ]
      },
      "faces": {
        "north": {
          "uv": [
            15.53125,
            7.9375,
            4.5625,
            7.90625
          ],
          "texture": "#2"
        },
        "east": {
          "uv": [
            15.53125,
            7.90625,
            15.5,
            7.9375
          ],
          "rotation": 90,
          "texture": "#2"
        },
        "south": {
          "uv": [
            4.5625,
            7.9375,
            15.53125,
            7.90625
          ],
          "texture": "#2"
        },
        "west": {
          "uv": [
            4.59375,
            7.90625,
            4.5625,
            7.9375
          ],
          "rotation": 270,
          "texture": "#2"
        },
        "up": {
          "uv": [
            4.5625,
            7.90625,
            15.53125,
            7.9375
          ],
          "texture": "#2"
        },
        "down": {
          "uv": [
            4.5625,
            7.9375,
            15.53125,
            7.90625
          ],
          "texture": "#2"
        }
      }
    },
    {
      "name": "kusanag612_blade_6",
      "from": [
        4.5625,
        7.95,
        7.9375
      ],
      "to": [
        15.5,
        8,
        7.96875
      ],
      "rotation": {
        "angle": 0,
        "axis": "y",
        "origin": [
          0,
          16,
          0
        ]
      },
      "faces": {
        "north": {
          "uv": [
            15.5,
            7.96875,
            4.5625,
            7.9375
          ],
          "texture": "#2"
        },
        "east": {
          "uv": [
            15.5,
            7.9375,
            15.46875,
            7.96875
          ],
          "rotation": 90,
          "texture": "#2"
        },
        "south": {
          "uv": [
            4.5625,
            7.96875,
            15.5,
            7.9375
          ],
          "texture": "#2"
        },
        "west": {
          "uv": [
            4.59375,
            7.9375,
            4.5625,
            7.96875
          ],
          "rotation": 270,
          "texture": "#2"
        },
        "up": {
          "uv": [
            4.5625,
            7.9375,
            15.5,
            7.96875
          ],
          "texture": "#2"
        },
        "down": {
          "uv": [
            4.5625,
            7.96875,
            15.5,
            7.9375
          ],
          "texture": "#2"
        }
      }
    },
    {
      "name": "kusanag512_blade_7",
      "from": [
        4.5625,
        7.95,
        7.96875
      ],
      "to": [
        15.5,
        8,
        8
      ],
      "rotation": {
        "angle": 0,
        "axis": "y",
        "origin": [
          0,
          16,
          0
        ]
      },
      "faces": {
        "north": {
          "uv": [
            15.5,
            8,
            4.5625,
            7.96875
          ],
          "texture": "#2"
        },
        "east": {
          "uv": [
            15.5,
            7.96875,
            15.46875,
            8
          ],
          "rotation": 90,
          "texture": "#2"
        },
        "south": {
          "uv": [
            4.5625,
            8,
            15.5,
            7.96875
          ],
          "texture": "#2"
        },
        "west": {
          "uv": [
            4.59375,
            7.96875,
            4.5625,
            8
          ],
          "rotation": 270,
          "texture": "#2"
        },
        "up": {
          "uv": [
            4.5625,
            7.96875,
            15.5,
            8
          ],
          "texture": "#2"
        },
        "down": {
          "uv": [
            4.5625,
            8,
            15.5,
            7.96875
          ],
          "texture": "#2"
        }
      }
    },
    {
      "name": "kusanag512_blade_8",
      "from": [
        4.5625,
        7.95,
        8
      ],
      "to": [
        15.5,
        8,
        8.03125
      ],
      "rotation": {
        "angle": 0,
        "axis": "y",
        "origin": [
          0,
          16,
          0
        ]
      },
      "faces": {
        "north": {
          "uv": [
            15.5,
            8.03125,
            4.5625,
            8
          ],
          "texture": "#2"
        },
        "east": {
          "uv": [
            15.5,
            8,
            15.46875,
            8.03125
          ],
          "rotation": 90,
          "texture": "#2"
        },
        "south": {
          "uv": [
            4.5625,
            8.03125,
            15.5,
            8
          ],
          "texture": "#2"
        },
        "west": {
          "uv": [
            4.59375,
            8,
            4.5625,
            8.03125
          ],
          "rotation": 270,
          "texture": "#2"
        },
        "up": {
          "uv": [
            4.5625,
            8,
            15.5,
            8.03125
          ],
          "texture": "#2"
        },
        "down": {
          "uv": [
            4.5625,
            8.03125,
            15.5,
            8
          ],
          "texture": "#2"
        }
      }
    },
    {
      "name": "kusanag512_blade_9",
      "from": [
        4.5625,
        7.95,
        8.03125
      ],
      "to": [
        15.4375,
        8,
        8.0625
      ],
      "rotation": {
        "angle": 0,
        "axis": "y",
        "origin": [
          0,
          16,
          0
        ]
      },
      "faces": {
        "north": {
          "uv": [
            15.4375,
            8.0625,
            4.5625,
            8.03125
          ],
          "texture": "#2"
        },
        "east": {
          "uv": [
            15.4375,
            8.03125,
            15.40625,
            8.0625
          ],
          "rotation": 90,
          "texture": "#2"
        },
        "south": {
          "uv": [
            4.5625,
            8.0625,
            15.4375,
            8.03125
          ],
          "texture": "#2"
        },
        "west": {
          "uv": [
            4.59375,
            8.03125,
            4.5625,
            8.0625
          ],
          "rotation": 270,
          "texture": "#2"
        },
        "up": {
          "uv": [
            4.5625,
            8.03125,
            15.4375,
            8.0625
          ],
          "texture": "#2"
        },
        "down": {
          "uv": [
            4.5625,
            8.0625,
            15.4375,
            8.03125
          ],
          "texture": "#2"
        }
      }
    },
    {
      "name": "kusanag512_blade_10",
      "from": [
        4.5625,
        7.955,
        8.0625
      ],
      "to": [
        15.4375,
        8,
        8.09375
      ],
      "rotation": {
        "angle": 0,
        "axis": "y",
        "origin": [
          0,
          16,
          0
        ]
      },
      "faces": {
        "north": {
          "uv": [
            15.4375,
            8.09375,
            4.5625,
            8.0625
          ],
          "texture": "#2"
        },
        "east": {
          "uv": [
            15.4375,
            8.0625,
            15.40625,
            8.09375
          ],
          "rotation": 90,
          "texture": "#2"
        },
        "south": {
          "uv": [
            4.5625,
            8.09375,
            15.4375,
            8.0625
          ],
          "texture": "#2"
        },
        "west": {
          "uv": [
            4.59375,
            8.0625,
            4.5625,
            8.09375
          ],
          "rotation": 270,
          "texture": "#2"
        },
        "up": {
          "uv": [
            4.5625,
            8.0625,
            15.4375,
            8.09375
          ],
          "texture": "#2"
        },
        "down": {
          "uv": [
            4.5625,
            8.09375,
            15.4375,
            8.0625
          ],
          "texture": "#2"
        }
      }
    },
    {
      "name": "kusanag512_blade_11",
      "from": [
        4.5625,
        7.96,
        8.09375
      ],
      "to": [
        15.40625,
        8,
        8.125
      ],
      "rotation": {
        "angle": 0,
        "axis": "y",
        "origin": [
          0,
          16,
          0
        ]
      },
      "faces": {
        "north": {
          "uv": [
            15.40625,
            8.125,
            4.5625,
            8.09375
          ],
          "texture": "#2"
        },
        "east": {
          "uv": [
            15.40625,
            8.09375,
            15.375,
            8.125
          ],
          "rotation": 90,
          "texture": "#2"
        },
        "south": {
          "uv": [
            4.5625,
            8.125,
            15.40625,
            8.09375
          ],
          "texture": "#2"
        },
        "west": {
          "uv": [
            4.59375,
            8.09375,
            4.5625,
            8.125
          ],
          "rotation": 270,
          "texture": "#2"
        },
        "up": {
          "uv": [
            4.5625,
            8.09375,
            15.40625,
            8.125
          ],
          "texture": "#2"
        },
        "down": {
          "uv": [
            4.5625,
            8.125,
            15.40625,
            8.09375
          ],
          "texture": "#2"
        }
      }
    },
    {
      "name": "kusanag512_blade_12",
      "from": [
        4.5625,
        7.965,
        8.125
      ],
      "to": [
        15.40625,
        8,
        8.15625
      ],
      "rotation": {
        "angle": 0,
        "axis": "y",
        "origin": [
          0,
          16,
          0
        ]
      },
      "faces": {
        "north": {
          "uv": [
            15.40625,
            8.15625,
            4.5625,
            8.125
          ],
          "texture": "#2"
        },
        "east": {
          "uv": [
            15.40625,
            8.125,
            15.375,
            8.15625
          ],
          "rotation": 90,
          "texture": "#2"
        },
        "south": {
          "uv": [
            4.5625,
            8.15625,
            15.40625,
            8.125
          ],
          "texture": "#2"
        },
        "west": {
          "uv": [
            4.59375,
            8.125,
            4.5625,
            8.15625
          ],
          "rotation": 270,
          "texture": "#2"
        },
        "up": {
          "uv": [
            4.5625,
            8.125,
            15.40625,
            8.15625
          ],
          "texture": "#2"
        },
        "down": {
          "uv": [
            4.5625,
            8.15625,
            15.40625,
            8.125
          ],
          "texture": "#2"
        }
      }
    },
    {
      "name": "kusanag513_blade_13",
      "from": [
        4.5625,
        7.97,
        8.15625
      ],
      "to": [
        15.375,
        8,
        8.1875
      ],
      "rotation": {
        "angle": 0,
        "axis": "y",
        "origin": [
          0,
          16,
          0
        ]
      },
      "faces": {
        "north": {
          "uv": [
            15.375,
            8.1875,
            4.5625,
            8.15625
          ],
          "texture": "#2"
        },
        "east": {
          "uv": [
            15.375,
            8.15625,
            15.34375,
            8.1875
          ],
          "rotation": 90,
          "texture": "#2"
        },
        "south": {
          "uv": [
            4.5625,
            8.1875,
            15.375,
            8.15625
          ],
          "texture": "#2"
        },
        "west": {
          "uv": [
            4.59375,
            8.15625,
            4.5625,
            8.1875
          ],
          "rotation": 270,
          "texture": "#2"
        },
        "up": {
          "uv": [
            4.5625,
            8.15625,
            15.375,
            8.1875
          ],
          "texture": "#2"
        },
        "down": {
          "uv": [
            4.5625,
            8.1875,
            15.375,
            8.15625
          ],
          "texture": "#2"
        }
      }
    },
    {
      "name": "kusanag512_blade_14",
      "from": [
        4.5625,
        7.975,
        8.1875
      ],
      "to": [
        15.3125,
        8,
        8.21875
      ],
      "rotation": {
        "angle": 0,
        "axis": "y",
        "origin": [
          0,
          16,
          0
        ]
      },
      "faces": {
        "north": {
          "uv": [
            15.3125,
            8.21875,
            4.5625,
            8.1875
          ],
          "texture": "#2"
        },
        "east": {
          "uv": [
            15.3125,
            8.1875,
            15.28125,
            8.21875
          ],
          "rotation": 90,
          "texture": "#2"
        },
        "south": {
          "uv": [
            4.5625,
            8.21875,
            15.3125,
            8.1875
          ],
          "texture": "#2"
        },
        "west": {
          "uv": [
            4.59375,
            8.1875,
            4.5625,
            8.21875
          ],
          "rotation": 270,
          "texture": "#2"
        },
        "up": {
          "uv": [
            4.5625,
            8.1875,
            15.3125,
            8.21875
          ],
          "texture": "#2"
        },
        "down": {
          "uv": [
            4.5625,
            8.21875,
            15.3125,
            8.1875
          ],
          "texture": "#2"
        }
      }
    },
    {
      "name": "kusanag512_blade_15",
      "from": [
        4.5625,
        7.98,
        8.21875
      ],
      "to": [
        15.3125,
        8,
        8.25
      ],
      "rotation": {
        "angle": 0,
        "axis": "y",
        "origin": [
          0,
          16,
          0
        ]
      },
      "faces": {
        "north": {
          "uv": [
            15.3125,
            8.25,
            4.5625,
            8.21875
          ],
          "texture": "#2"
        },
        "east": {
          "uv": [
            15.3125,
            8.21875,
            15.28125,
            8.25
          ],
          "rotation": 90,
          "texture": "#2"
        },
        "south": {
          "uv": [
            4.5625,
            8.25,
            15.3125,
            8.21875
          ],
          "texture": "#2"
        },
        "west": {
          "uv": [
            4.59375,
            8.21875,
            4.5625,
            8.25
          ],
          "rotation": 270,
          "texture": "#2"
        },
        "up": {
          "uv": [
            4.5625,
            8.21875,
            15.3125,
            8.25
          ],
          "texture": "#2"
        },
        "down": {
          "uv": [
            4.5625,
            8.25,
            15.3125,
            8.21875
          ],
          "texture": "#2"
        }
      }
    },
    {
      "name": "kusanag512_blade_16",
      "from": [
        4.5625,
        7.985,
        8.25
      ],
      "to": [
        15.28125,
        8,
        8.28125
      ],
      "rotation": {
        "angle": 0,
        "axis": "y",
        "origin": [
          0,
          16,
          0
        ]
      },
      "faces": {
        "north": {
          "uv": [
            15.28125,
            8.28125,
            4.5625,
            8.25
          ],
          "texture": "#2"
        },
        "east": {
          "uv": [
            15.28125,
            8.25,
            15.25,
            8.28125
          ],
          "rotation": 90,
          "texture": "#2"
        },
        "south": {
          "uv": [
            4.5625,
            8.28125,
            15.28125,
            8.25
          ],
          "texture": "#2"
        },
        "west": {
          "uv": [
            4.59375,
            8.25,
            4.5625,
            8.28125
          ],
          "rotation": 270,
          "texture": "#2"
        },
        "up": {
          "uv": [
            4.5625,
            8.25,
            15.28125,
            8.28125
          ],
          "texture": "#2"
        },
        "down": {
          "uv": [
            4.5625,
            8.28125,
            15.28125,
            8.25
          ],
          "texture": "#2"
        }
      }
    },
    {
      "name": "kusanag512_blade_17",
      "from": [
        4.5625,
        7.99,
        8.28125
      ],
      "to": [
        15.25,
        8,
        8.3125
      ],
      "rotation": {
        "angle": 0,
        "axis": "y",
        "origin": [
          0,
          16,
          0
        ]
      },
      "faces": {
        "north": {
          "uv": [
            15.25,
            8.3125,
            4.5625,
            8.28125
          ],
          "texture": "#2"
        },
        "east": {
          "uv": [
            15.25,
            8.28125,
            15.21875,
            8.3125
          ],
          "rotation": 90,
          "texture": "#2"
        },
        "south": {
          "uv": [
            4.5625,
            8.3125,
            15.25,
            8.28125
          ],
          "texture": "#2"
        },
        "west": {
          "uv": [
            4.59375,
            8.28125,
            4.5625,
            8.3125
          ],
          "rotation": 270,
          "texture": "#2"
        },
        "up": {
          "uv": [
            4.5625,
            8.28125,
            15.25,
            8.3125
          ],
          "texture": "#2"
        },
        "down": {
          "uv": [
            4.5625,
            8.3125,
            15.25,
            8.28125
          ],
          "texture": "#2"
        }
      }
    },
    {
      "name": "kusanag512_blade_18",
      "from": [
        4.5625,
        7.995,
        8.3125
      ],
      "to": [
        15.21875,
        8,
        8.34375
      ],
      "rotation": {
        "angle": 0,
        "axis": "y",
        "origin": [
          0,
          16,
          0
        ]
      },
      "faces": {
        "north": {
          "uv": [
            15.21875,
            8.34375,
            4.5625,
            8.3125
          ],
          "texture": "#2"
        },
        "east": {
          "uv": [
            15.21875,
            8.3125,
            15.1875,
            8.34375
          ],
          "rotation": 90,
          "texture": "#2"
        },
        "south": {
          "uv": [
            4.5625,
            8.34375,
            15.21875,
            8.3125
          ],
          "texture": "#2"
        },
        "west": {
          "uv": [
            4.59375,
            8.3125,
            4.5625,
            8.34375
          ],
          "rotation": 270,
          "texture": "#2"
        },
        "up": {
          "uv": [
            4.5625,
            8.3125,
            15.21875,
            8.34375
          ],
          "texture": "#2"
        },
        "down": {
          "uv": [
            4.5625,
            8.34375,
            15.21875,
            8.3125
          ],
          "texture": "#2"
        }
      }
    },
    {
      "name": "kusanag512_blade_30",
      "from": [
        7.5,
        8,
        8.34375
      ],
      "to": [
        15.125,
        8,
        8.375
      ],
      "rotation": {
        "angle": 0,
        "axis": "y",
        "origin": [
          0,
          16,
          0
        ]
      },
      "faces": {
        "north": {
          "uv": [
            15.125,
            8.375,
            7.5,
            8.34375
          ],
          "texture": "#2"
        },
        "east": {
          "uv": [
            15.125,
            8.34375,
            15.09375,
            8.375
          ],
          "rotation": 90,
          "texture": "#2"
        },
        "south": {
          "uv": [
            7.5,
            8.375,
            15.125,
            8.34375
          ],
          "texture": "#2"
        },
        "west": {
          "uv": [
            7.53125,
            8.34375,
            7.5,
            8.375
          ],
          "rotation": 270,
          "texture": "#2"
        },
        "up": {
          "uv": [
            7.5,
            8.34375,
            15.125,
            8.375
          ],
          "texture": "#2"
        },
        "down": {
          "uv": [
            7.5,
            8.375,
            15.125,
            8.34375
          ],
          "texture": "#2"
        }
      }
    },
    {
      "name": "kusanag512_hilt_0",
      "from": [
        0.65625,
        7.85,
        7.71875
      ],
      "to": [
        4.09375,
        8.15,
        7.75
      ],
      "faces": {
        "north": {
          "uv": [
            4.09375,
            7.71875,
            0.65625,
            7.75
          ],
          "texture": "#2"
        },
        "east": {
          "uv": [
            4.0625,
            7.71875,
            4.09375,
            7.75
          ],
          "rotation": 90,
          "texture": "#2"
        },
        "south": {
          "uv": [
            0.65625,
            7.71875,
            4.09375,
            7.75
          ],
          "texture": "#2"
        },
        "west": {
          "uv": [
            0.65625,
            7.71875,
            0.6875,
            7.75
          ],
          "rotation": 270,
          "texture": "#2"
        },
        "up": {
          "uv": [
            0.65625,
            7.71875,
            4.09375,
            7.75
          ],
          "texture": "#2"
        },
        "down": {
          "uv": [
            0.65625,
            7.75,
            4.09375,
            7.71875
          ],
          "texture": "#2"
        }
      }
    },
    {
      "name": "kusanag512_hilt_1",
      "from": [
        0.625,
        7.85,
        7.75
      ],
      "to": [
        4.21875,
        8.15,
        7.78125
      ],
      "faces": {
        "north": {
          "uv": [
            4.21875,
            7.75,
            0.625,
            7.78125
          ],
          "texture": "#2"
        },
        "east": {
          "uv": [
            4.1875,
            7.75,
            4.21875,
            7.78125
          ],
          "rotation": 90,
          "texture": "#2"
        },
        "south": {
          "uv": [
            0.625,
            7.75,
            4.21875,
            7.78125
          ],
          "texture": "#2"
        },
        "west": {
          "uv": [
            0.625,
            7.75,
            0.65625,
            7.78125
          ],
          "rotation": 270,
          "texture": "#2"
        },
        "up": {
          "uv": [
            0.625,
            7.75,
            4.21875,
            7.78125
          ],
          "texture": "#2"
        },
        "down": {
          "uv": [
            0.625,
            7.78125,
            4.21875,
            7.75
          ],
          "texture": "#2"
        }
      }
    },
    {
      "name": "kusanag512_hilt_2",
      "from": [
        0.625,
        7.85,
        7.78125
      ],
      "to": [
        4.21875,
        8.15,
        7.8125
      ],
      "faces": {
        "north": {
          "uv": [
            4.21875,
            7.78125,
            0.625,
            7.8125
          ],
          "texture": "#2"
        },
        "east": {
          "uv": [
            4.1875,
            7.78125,
            4.21875,
            7.8125
          ],
          "rotation": 90,
          "texture": "#2"
        },
        "south": {
          "uv": [
            0.625,
            7.78125,
            4.21875,
            7.8125
          ],
          "texture": "#2"
        },
        "west": {
          "uv": [
            0.625,
            7.78125,
            0.65625,
            7.8125
          ],
          "rotation": 270,
          "texture": "#2"
        },
        "up": {
          "uv": [
            0.625,
            7.78125,
            4.21875,
            7.8125
          ],
          "texture": "#2"
        },
        "down": {
          "uv": [
            0.625,
            7.8125,
            4.21875,
            7.78125
          ],
          "texture": "#2"
        }
      }
    },
    {
      "name": "kusanag512_hilt_3",
      "from": [
        0.625,
        7.85,
        7.8125
      ],
      "to": [
        4.5625,
        8.15,
        7.84375
      ],
      "faces": {
        "north": {
          "uv": [
            4.5625,
            7.8125,
            0.625,
            7.84375
          ],
          "texture": "#2"
        },
        "east": {
          "uv": [
            4.53125,
            7.8125,
            4.5625,
            7.84375
          ],
          "rotation": 90,
          "texture": "#2"
        },
        "south": {
          "uv": [
            0.625,
            7.8125,
            4.5625,
            7.84375
          ],
          "texture": "#2"
        },
        "west": {
          "uv": [
            0.625,
            7.8125,
            0.65625,
            7.84375
          ],
          "rotation": 270,
          "texture": "#2"
        },
        "up": {
          "uv": [
            0.625,
            7.8125,
            4.5625,
            7.84375
          ],
          "texture": "#2"
        },
        "down": {
          "uv": [
            0.625,
            7.84375,
            4.5625,
            7.8125
          ],
          "texture": "#2"
        }
      }
    },
    {
      "name": "kusanag512_hilt_4",
      "from": [
        0.625,
        7.85,
        7.84375
      ],
      "to": [
        4.5625,
        8.15,
        7.875
      ],
      "faces": {
        "north": {
          "uv": [
            4.5625,
            7.84375,
            0.625,
            7.875
          ],
          "texture": "#2"
        },
        "east": {
          "uv": [
            4.53125,
            7.84375,
            4.5625,
            7.875
          ],
          "rotation": 90,
          "texture": "#2"
        },
        "south": {
          "uv": [
            0.625,
            7.84375,
            4.5625,
            7.875
          ],
          "texture": "#2"
        },
        "west": {
          "uv": [
            0.625,
            7.84375,
            0.65625,
            7.875
          ],
          "rotation": 270,
          "texture": "#2"
        },
        "up": {
          "uv": [
            0.625,
            7.84375,
            4.5625,
            7.875
          ],
          "texture": "#2"
        },
        "down": {
          "uv": [
            0.625,
            7.875,
            4.5625,
            7.84375
          ],
          "texture": "#2"
        }
      }
    },
    {
      "name": "kusanag512_hilt_5",
      "from": [
        0.59375,
        7.85,
        7.875
      ],
      "to": [
        4.5625,
        8.15,
        7.90625
      ],
      "faces": {
        "north": {
          "uv": [
            4.5625,
            7.875,
            0.59375,
            7.90625
          ],
          "texture": "#2"
        },
        "east": {
          "uv": [
            4.53125,
            7.875,
            4.5625,
            7.90625
          ],
          "rotation": 90,
          "texture": "#2"
        },
        "south": {
          "uv": [
            0.59375,
            7.875,
            4.5625,
            7.90625
          ],
          "texture": "#2"
        },
        "west": {
          "uv": [
            0.59375,
            7.875,
            0.625,
            7.90625
          ],
          "rotation": 270,
          "texture": "#2"
        },
        "up": {
          "uv": [
            0.59375,
            7.875,
            4.5625,
            7.90625
          ],
          "texture": "#2"
        },
        "down": {
          "uv": [
            0.59375,
            7.90625,
            4.5625,
            7.875
          ],
          "texture": "#2"
        }
      }
    },
    {
      "name": "kusanag512_hilt_6",
      "from": [
        0.59375,
        7.85,
        7.90625
      ],
      "to": [
        4.5625,
        8.15,
        7.9375
      ],
      "faces": {
        "north": {
          "uv": [
            4.5625,
            7.90625,
            0.59375,
            7.9375
          ],
          "texture": "#2"
        },
        "east": {
          "uv": [
            4.53125,
            7.90625,
            4.5625,
            7.9375
          ],
          "rotation": 90,
          "texture": "#2"
        },
        "south": {
          "uv": [
            0.59375,
            7.90625,
            4.5625,
            7.9375
          ],
          "texture": "#2"
        },
        "west": {
          "uv": [
            0.59375,
            7.90625,
            0.625,
            7.9375
          ],
          "rotation": 270,
          "texture": "#2"
        },
        "up": {
          "uv": [
            0.59375,
            7.90625,
            4.5625,
            7.9375
          ],
          "texture": "#2"
        },
        "down": {
          "uv": [
            0.59375,
            7.9375,
            4.5625,
            7.90625
          ],
          "texture": "#2"
        }
      }
    },
    {
      "name": "kusanag512_hilt_7",
      "from": [
        0.59375,
        7.85,
        7.9375
      ],
      "to": [
        4.5625,
        8.15,
        7.96875
      ],
      "faces": {
        "north": {
          "uv": [
            4.5625,
            7.9375,
            0.59375,
            7.96875
          ],
          "texture": "#2"
        },
        "east": {
          "uv": [
            4.53125,
            7.9375,
            4.5625,
            7.96875
          ],
          "rotation": 90,
          "texture": "#2"
        },
        "south": {
          "uv": [
            0.59375,
            7.9375,
            4.5625,
            7.96875
          ],
          "texture": "#2"
        },
        "west": {
          "uv": [
            0.59375,
            7.9375,
            0.625,
            7.96875
          ],
          "rotation": 270,
          "texture": "#2"
        },
        "up": {
          "uv": [
            0.59375,
            7.9375,
            4.5625,
            7.96875
          ],
          "texture": "#2"
        },
        "down": {
          "uv": [
            0.59375,
            7.96875,
            4.5625,
            7.9375
          ],
          "texture": "#2"
        }
      }
    },
    {
      "name": "kusanag512_hilt_8",
      "from": [
        0.59375,
        7.85,
        7.96875
      ],
      "to": [
        4.5625,
        8.15,
        8
      ],
      "faces": {
        "north": {
          "uv": [
            4.5625,
            7.96875,
            0.59375,
            8
          ],
          "texture": "#2"
        },
        "east": {
          "uv": [
            4.53125,
            7.96875,
            4.5625,
            8
          ],
          "rotation": 90,
          "texture": "#2"
        },
        "south": {
          "uv": [
            0.59375,
            7.96875,
            4.5625,
            8
          ],
          "texture": "#2"
        },
        "west": {
          "uv": [
            0.59375,
            7.96875,
            0.625,
            8
          ],
          "rotation": 270,
          "texture": "#2"
        },
        "up": {
          "uv": [
            0.59375,
            7.96875,
            4.5625,
            8
          ],
          "texture": "#2"
        },
        "down": {
          "uv": [
            0.59375,
            8,
            4.5625,
            7.96875
          ],
          "texture": "#2"
        }
      }
    },
    {
      "name": "kusanag512_hilt_9",
      "from": [
        0.59375,
        7.85,
        8
      ],
      "to": [
        4.5625,
        8.15,
        8.03125
      ],
      "faces": {
        "north": {
          "uv": [
            4.5625,
            8,
            0.59375,
            8.03125
          ],
          "texture": "#2"
        },
        "east": {
          "uv": [
            4.53125,
            8,
            4.5625,
            8.03125
          ],
          "rotation": 90,
          "texture": "#2"
        },
        "south": {
          "uv": [
            0.59375,
            8,
            4.5625,
            8.03125
          ],
          "texture": "#2"
        },
        "west": {
          "uv": [
            0.59375,
            8,
            0.625,
            8.03125
          ],
          "rotation": 270,
          "texture": "#2"
        },
        "up": {
          "uv": [
            0.59375,
            8,
            4.5625,
            8.03125
          ],
          "texture": "#2"
        },
        "down": {
          "uv": [
            0.59375,
            8.03125,
            4.5625,
            8
          ],
          "texture": "#2"
        }
      }
    },
    {
      "name": "kusanag512_hilt_10",
      "from": [
        0.59375,
        7.85,
        8.03125
      ],
      "to": [
        4.5625,
        8.15,
        8.0625
      ],
      "faces": {
        "north": {
          "uv": [
            4.5625,
            8.03125,
            0.59375,
            8.0625
          ],
          "texture": "#2"
        },
        "east": {
          "uv": [
            4.53125,
            8.03125,
            4.5625,
            8.0625
          ],
          "rotation": 90,
          "texture": "#2"
        },
        "south": {
          "uv": [
            0.59375,
            8.03125,
            4.5625,
            8.0625
          ],
          "texture": "#2"
        },
        "west": {
          "uv": [
            0.59375,
            8.03125,
            0.625,
            8.0625
          ],
          "rotation": 270,
          "texture": "#2"
        },
        "up": {
          "uv": [
            0.59375,
            8.03125,
            4.5625,
            8.0625
          ],
          "texture": "#2"
        },
        "down": {
          "uv": [
            0.59375,
            8.0625,
            4.5625,
            8.03125
          ],
          "texture": "#2"
        }
      }
    },
    {
      "name": "kusanag512_hilt_11",
      "from": [
        0.59375,
        7.85,
        8.0625
      ],
      "to": [
        4.5625,
        8.15,
        8.09375
      ],
      "faces": {
        "north": {
          "uv": [
            4.5625,
            8.0625,
            0.59375,
            8.09375
          ],
          "texture": "#2"
        },
        "east": {
          "uv": [
            4.53125,
            8.0625,
            4.5625,
            8.09375
          ],
          "rotation": 90,
          "texture": "#2"
        },
        "south": {
          "uv": [
            0.59375,
            8.0625,
            4.5625,
            8.09375
          ],
          "texture": "#2"
        },
        "west": {
          "uv": [
            0.59375,
            8.0625,
            0.625,
            8.09375
          ],
          "rotation": 270,
          "texture": "#2"
        },
        "up": {
          "uv": [
            0.59375,
            8.0625,
            4.5625,
            8.09375
          ],
          "texture": "#2"
        },
        "down": {
          "uv": [
            0.59375,
            8.09375,
            4.5625,
            8.0625
          ],
          "texture": "#2"
        }
      }
    },
    {
      "name": "kusanag512_hilt_12",
      "from": [
        0.59375,
        7.85,
        8.09375
      ],
      "to": [
        4.5625,
        8.15,
        8.125
      ],
      "faces": {
        "north": {
          "uv": [
            4.5625,
            8.09375,
            0.59375,
            8.125
          ],
          "texture": "#2"
        },
        "east": {
          "uv": [
            4.53125,
            8.09375,
            4.5625,
            8.125
          ],
          "rotation": 90,
          "texture": "#2"
        },
        "south": {
          "uv": [
            0.59375,
            8.09375,
            4.5625,
            8.125
          ],
          "texture": "#2"
        },
        "west": {
          "uv": [
            0.59375,
            8.09375,
            0.625,
            8.125
          ],
          "rotation": 270,
          "texture": "#2"
        },
        "up": {
          "uv": [
            0.59375,
            8.09375,
            4.5625,
            8.125
          ],
          "texture": "#2"
        },
        "down": {
          "uv": [
            0.59375,
            8.125,
            4.5625,
            8.09375
          ],
          "texture": "#2"
        }
      }
    },
    {
      "name": "kusanag512_hilt_13",
      "from": [
        0.59375,
        7.85,
        8.125
      ],
      "to": [
        4.5625,
        8.15,
        8.15625
      ],
      "faces": {
        "north": {
          "uv": [
            4.5625,
            8.125,
            0.59375,
            8.15625
          ],
          "texture": "#2"
        },
        "east": {
          "uv": [
            4.53125,
            8.125,
            4.5625,
            8.15625
          ],
          "rotation": 90,
          "texture": "#2"
        },
        "south": {
          "uv": [
            0.59375,
            8.125,
            4.5625,
            8.15625
          ],
          "texture": "#2"
        },
        "west": {
          "uv": [
            0.59375,
            8.125,
            0.625,
            8.15625
          ],
          "rotation": 270,
          "texture": "#2"
        },
        "up": {
          "uv": [
            0.59375,
            8.125,
            4.5625,
            8.15625
          ],
          "texture": "#2"
        },
        "down": {
          "uv": [
            0.59375,
            8.15625,
            4.5625,
            8.125
          ],
          "texture": "#2"
        }
      }
    },
    {
      "name": "kusanag512_hilt_14",
      "from": [
        0.59375,
        7.85,
        8.15625
      ],
      "to": [
        4.5625,
        8.15,
        8.1875
      ],
      "faces": {
        "north": {
          "uv": [
            4.5625,
            8.15625,
            0.59375,
            8.1875
          ],
          "texture": "#2"
        },
        "east": {
          "uv": [
            4.53125,
            8.15625,
            4.5625,
            8.1875
          ],
          "rotation": 90,
          "texture": "#2"
        },
        "south": {
          "uv": [
            0.59375,
            8.15625,
            4.5625,
            8.1875
          ],
          "texture": "#2"
        },
        "west": {
          "uv": [
            0.59375,
            8.15625,
            0.625,
            8.1875
          ],
          "rotation": 270,
          "texture": "#2"
        },
        "up": {
          "uv": [
            0.59375,
            8.15625,
            4.5625,
            8.1875
          ],
          "texture": "#2"
        },
        "down": {
          "uv": [
            0.59375,
            8.1875,
            4.5625,
            8.15625
          ],
          "texture": "#2"
        }
      }
    },
    {
      "name": "kusanag512_hilt_15",
      "from": [
        0.59375,
        7.85,
        8.1875
      ],
      "to": [
        4.5625,
        8.15,
        8.21875
      ],
      "faces": {
        "north": {
          "uv": [
            4.5625,
            8.1875,
            0.59375,
            8.21875
          ],
          "texture": "#2"
        },
        "east": {
          "uv": [
            4.53125,
            8.1875,
            4.5625,
            8.21875
          ],
          "rotation": 90,
          "texture": "#2"
        },
        "south": {
          "uv": [
            0.59375,
            8.1875,
            4.5625,
            8.21875
          ],
          "texture": "#2"
        },
        "west": {
          "uv": [
            0.59375,
            8.1875,
            0.625,
            8.21875
          ],
          "rotation": 270,
          "texture": "#2"
        },
        "up": {
          "uv": [
            0.59375,
            8.1875,
            4.5625,
            8.21875
          ],
          "texture": "#2"
        },
        "down": {
          "uv": [
            0.59375,
            8.21875,
            4.5625,
            8.1875
          ],
          "texture": "#2"
        }
      }
    },
    {
      "name": "kusanag512_hilt_16",
      "from": [
        0.59375,
        7.85,
        8.21875
      ],
      "to": [
        4.5625,
        8.15,
        8.25
      ],
      "faces": {
        "north": {
          "uv": [
            4.5625,
            8.21875,
            0.59375,
            8.25
          ],
          "texture": "#2"
        },
        "east": {
          "uv": [
            4.53125,
            8.21875,
            4.5625,
            8.25
          ],
          "rotation": 90,
          "texture": "#2"
        },
        "south": {
          "uv": [
            0.59375,
            8.21875,
            4.5625,
            8.25
          ],
          "texture": "#2"
        },
        "west": {
          "uv": [
            0.59375,
            8.21875,
            0.625,
            8.25
          ],
          "rotation": 270,
          "texture": "#2"
        },
        "up": {
          "uv": [
            0.59375,
            8.21875,
            4.5625,
            8.25
          ],
          "texture": "#2"
        },
        "down": {
          "uv": [
            0.59375,
            8.25,
            4.5625,
            8.21875
          ],
          "texture": "#2"
        }
      }
    },
    {
      "name": "kusanag512_hilt_17",
      "from": [
        0.59375,
        7.85,
        8.25
      ],
      "to": [
        4.5625,
        8.15,
        8.28125
      ],
      "faces": {
        "north": {
          "uv": [
            4.5625,
            8.25,
            0.59375,
            8.28125
          ],
          "texture": "#2"
        },
        "east": {
          "uv": [
            4.53125,
            8.25,
            4.5625,
            8.28125
          ],
          "rotation": 90,
          "texture": "#2"
        },
        "south": {
          "uv": [
            0.59375,
            8.25,
            4.5625,
            8.28125
          ],
          "texture": "#2"
        },
        "west": {
          "uv": [
            0.59375,
            8.25,
            0.625,
            8.28125
          ],
          "rotation": 270,
          "texture": "#2"
        },
        "up": {
          "uv": [
            0.59375,
            8.25,
            4.5625,
            8.28125
          ],
          "texture": "#2"
        },
        "down": {
          "uv": [
            0.59375,
            8.28125,
            4.5625,
            8.25
          ],
          "texture": "#2"
        }
      }
    },
    {
      "name": "kusanag512_hilt_18",
      "from": [
        0.59375,
        7.85,
        8.28125
      ],
      "to": [
        4.5625,
        8.15,
        8.3125
      ],
      "faces": {
        "north": {
          "uv": [
            4.5625,
            8.28125,
            0.59375,
            8.3125
          ],
          "texture": "#2"
        },
        "east": {
          "uv": [
            4.53125,
            8.28125,
            4.5625,
            8.3125
          ],
          "rotation": 90,
          "texture": "#2"
        },
        "south": {
          "uv": [
            0.59375,
            8.28125,
            4.5625,
            8.3125
          ],
          "texture": "#2"
        },
        "west": {
          "uv": [
            0.59375,
            8.28125,
            0.625,
            8.3125
          ],
          "rotation": 270,
          "texture": "#2"
        },
        "up": {
          "uv": [
            0.59375,
            8.28125,
            4.5625,
            8.3125
          ],
          "texture": "#2"
        },
        "down": {
          "uv": [
            0.59375,
            8.3125,
            4.5625,
            8.28125
          ],
          "texture": "#2"
        }
      }
    },
    {
      "name": "kusanag512_hilt_19",
      "from": [
        0.625,
        7.85,
        8.3125
      ],
      "to": [
        4.5625,
        8.15,
        8.34375
      ],
      "faces": {
        "north": {
          "uv": [
            4.5625,
            8.3125,
            0.625,
            8.34375
          ],
          "texture": "#2"
        },
        "east": {
          "uv": [
            4.53125,
            8.3125,
            4.5625,
            8.34375
          ],
          "rotation": 90,
          "texture": "#2"
        },
        "south": {
          "uv": [
            0.625,
            8.3125,
            4.5625,
            8.34375
          ],
          "texture": "#2"
        },
        "west": {
          "uv": [
            0.625,
            8.3125,
            0.65625,
            8.34375
          ],
          "rotation": 270,
          "texture": "#2"
        },
        "up": {
          "uv": [
            0.625,
            8.3125,
            4.5625,
            8.34375
          ],
          "texture": "#2"
        },
        "down": {
          "uv": [
            0.625,
            8.34375,
            4.5625,
            8.3125
          ],
          "texture": "#2"
        }
      }
    },
    {
      "name": "kusanag512_hilt_20",
      "from": [
        0.65625,
        7.85,
        8.34375
      ],
      "to": [
        4.21875,
        8.15,
        8.375
      ],
      "faces": {
        "north": {
          "uv": [
            4.21875,
            8.34375,
            0.65625,
            8.375
          ],
          "texture": "#2"
        },
        "east": {
          "uv": [
            4.1875,
            8.34375,
            4.21875,
            8.375
          ],
          "rotation": 90,
          "texture": "#2"
        },
        "south": {
          "uv": [
            0.65625,
            8.34375,
            4.21875,
            8.375
          ],
          "texture": "#2"
        },
        "west": {
          "uv": [
            0.65625,
            8.34375,
            0.6875,
            8.375
          ],
          "rotation": 270,
          "texture": "#2"
        },
        "up": {
          "uv": [
            0.65625,
            8.34375,
            4.21875,
            8.375
          ],
          "texture": "#2"
        },
        "down": {
          "uv": [
            0.65625,
            8.375,
            4.21875,
            8.34375
          ],
          "texture": "#2"
        }
      }
    },
    {
      "name": "kusanag512_hilt_21",
      "from": [
        0.68,
        7.85,
        8.375
      ],
      "to": [
        4.095,
        8.15,
        8.40625
      ],
      "faces": {
        "north": {
          "uv": [
            0.6875,
            8.375,
            4.09375,
            8.40625
          ],
          "texture": "#2"
        },
        "east": {
          "uv": [
            0.6875,
            8.375,
            4.09375,
            8.40625
          ],
          "texture": "#2"
        },
        "south": {
          "uv": [
            0.6875,
            8.375,
            4.09375,
            8.40625
          ],
          "texture": "#2"
        },
        "west": {
          "uv": [
            0.6875,
            8.375,
            4.09375,
            8.40625
          ],
          "texture": "#2"
        },
        "up": {
          "uv": [
            0.6875,
            8.375,
            4.09375,
            8.40625
          ],
          "texture": "#2"
        },
        "down": {
          "uv": [
            0.6875,
            8.375,
            4.09375,
            8.40625
          ],
          "texture": "#2"
        }
      }
    }
  ],
  "display": {
    "thirdperson_righthand": {
      "rotation": [
        -10,
        -180,
        90
      ],
      "translation": [
        0,
        8,
        0.25
      ],
      "scale": [
        2,
        3,
        2.25
      ]
    },
    "thirdperson_lefthand": {
      "rotation": [
        -10,
        -180,
        -90
      ],
      "translation": [
        0,
        8,
        0.25
      ],
      "scale": [
        2,
        3,
        2.25
      ]
    },
    "firstperson_righthand": {
      "rotation": [
        -10,
        -180,
        90
      ],
      "translation": [
        0,
        8,
        0.25
      ],
      "scale": [
        2,
        3,
        2.25
      ]
    },
    "firstperson_lefthand": {
      "rotation": [
        -10,
        -180,
        -90
      ],
      "translation": [
        0,
        8,
        0.25
      ],
      "scale": [
        2,
        3,
        2.25
      ]
    },
    "ground": {
      "rotation": [
        0,
        0,
        -90
      ],
      "translation": [
        0,
        10,
        0
      ],
      "scale": [
        2,
        3,
        2.25
      ]
    },
    "gui": {
      "rotation": [
        90,
        46,
        0
      ],
      "translation": [
        0,
        0,
        -0.25
      ],
      "scale": [
        1.5,
        2,
        1.75
      ]
    },
    "head": {
      "rotation": [
        90,
        -160,
        0
      ],
      "translation": [
        0,
        -23,
        4
      ],
      "scale": [
        3,
        4,
        3.5
      ]
    },
    "fixed": {
      "rotation": [
        -90,
        -135,
        0
      ],
      "translation": [
        0,
        0,
        -0.25
      ],
      "scale": [
        1.8,
        2.75,
        2.1
      ]
    }
  },
  "groups": [
    {
      "name": "group",
      "origin": [
        8,
        8,
        8
      ],
      "color": 0,
      "children": [
        {
          "name": "kusanag512_blade",
          "origin": [
            8,
            8,
            8
          ],
          "color": 0,
          "children": [
            0,
            1,
            2,
            3,
            4,
            5,
            6,
            7,
            8,
            9,
            10,
            11,
            12,
            13,
            14,
            15,
            16,
            17
          ]
        },
        {
          "name": "kusanag512_blade",
          "origin": [
            8,
            8,
            8
          ],
          "color": 0,
          "children": [
            18,
            19,
            20,
            21,
            22,
            23,
            24,
            25,
            26,
            27,
            28,
            29,
            30,
            31,
            32,
            33,
            34,
            35
          ]
        },
        {
          "name": "kusanag512_hilt",
          "origin": [
            8,
            8,
            8
          ],
          "color": 0,
          "children": [
            36,
            37,
            38,
            39,
            40,
            41,
            42,
            43,
            44,
            45,
            46,
            47,
            48,
            49,
            50,
            51,
            52,
            53,
            54,
            55,
            56,
            57
          ]
        }
      ]
    }
  ]
}